pyimpute/__init__.py
pyimpute/_main.py
pyimpute-0.2.dist-info/LICENSE.txt
pyimpute-0.2.dist-info/METADATA
pyimpute-0.2.dist-info/WHEEL
pyimpute-0.2.dist-info/top_level.txt
pyimpute-0.2.dist-info/RECORD
