Metadata-Version: 2.1
Name: pyimpute
Version: 0.2
Summary: Utilities for applying scikit-learn to spatial datasets
Home-page: https://github.com/perrygeo/pyimpute
Author: Matthew Perry
Author-email: perrygeo@gmail.com
License: BSD
Keywords: gis geospatial geographic raster vector zonal statistics machinelearning
Platform: UNKNOWN
Classifier: Development Status :: 3 - Alpha
Classifier: Topic :: Utilities
Classifier: License :: OSI Approved :: BSD License
Classifier: Intended Audience :: Developers
Classifier: Intended Audience :: Science/Research
Classifier: Operating System :: OS Independent
Classifier: Programming Language :: Python :: 3
Classifier: Topic :: Scientific/Engineering :: GIS
Requires-Dist: scikit-learn
Requires-Dist: scipy
Requires-Dist: numpy
Requires-Dist: rasterstats
Requires-Dist: rasterio
